fastcrypto/__init__.py
fastcrypto/fastcrypto.so
fastcrypto/test_py.py
fastcrypto/version_config.py
fastcrypto-0.0.3.dist-info/METADATA
fastcrypto-0.0.3.dist-info/WHEEL
fastcrypto-0.0.3.dist-info/top_level.txt
fastcrypto-0.0.3.dist-info/RECORD
